mcbridge/__init__.py
mcbridge/__main__.py
mcbridge/agent.py
mcbridge/ap.py
mcbridge/cli.py
mcbridge/common.py
mcbridge/dns.py
mcbridge/init.py
mcbridge/paths.py
mcbridge/privileges.py
mcbridge/service_enablement.py
mcbridge/socket_helper.py
mcbridge/systemd_units.py
mcbridge/upstream.py
mcbridge/upstream_dns.py
mcbridge/resources/__init__.py
mcbridge/resources/knownservers.json
mcbridge/resources/provision.sh
mcbridge/web/__init__.py
mcbridge/web/config.py
mcbridge/web/wifi.py
mcbridge/web/static/css/app.css
mcbridge/web/static/docs/DESIGN.md
mcbridge/web/static/docs/DEVELOPER_ROADMAP.md
mcbridge/web/static/docs/INSTALL.md
mcbridge/web/static/docs/Overview.md
mcbridge/web/static/docs/PROVISIONING.md
mcbridge/web/static/docs/USAGE.md
mcbridge/web/static/js/app.js
mcbridge/web/static/js/docs.js
mcbridge/web/static/js/theme.js
mcbridge/web/templates/docs.html
mcbridge/web/templates/index.html
mcbridge-0.1.4.dist-info/METADATA
mcbridge-0.1.4.dist-info/WHEEL
mcbridge-0.1.4.dist-info/entry_points.txt
mcbridge-0.1.4.dist-info/top_level.txt
mcbridge-0.1.4.dist-info/RECORD
