Metadata-Version: 2.4
Name: mcbridge
Version: 0.1.4
Summary: Lightweight Minecraft Wi-Fi bridge appliance with AP and DNS management
Author: mcbridge maintainers
License: MIT
Requires-Python: >=3.9
Requires-Dist: Flask>=2.3
